pymolresponse/__init__.py
pymolresponse/_version.py
pymolresponse/ao2mo.py
pymolresponse/constants.py
pymolresponse/core.py
pymolresponse/cphf.py
pymolresponse/explicit_equations_full.py
pymolresponse/explicit_equations_partial.py
pymolresponse/helpers.py
pymolresponse/integrals.py
pymolresponse/molecular_property.py
pymolresponse/operators.py
pymolresponse/py.typed
pymolresponse/solvers.py
pymolresponse/td.py
pymolresponse/utils.py
pymolresponse/data/__init__.py
pymolresponse/interfaces/dalton/__init__.py
pymolresponse/interfaces/dalton/utils.py
pymolresponse/interfaces/psi4/__init__.py
pymolresponse/interfaces/psi4/integrals.py
pymolresponse/interfaces/psi4/molecules.py
pymolresponse/interfaces/psi4/utils.py
pymolresponse/interfaces/pyscf/__init__.py
pymolresponse/interfaces/pyscf/ao2mo.py
pymolresponse/interfaces/pyscf/helpers.py
pymolresponse/interfaces/pyscf/integrals.py
pymolresponse/interfaces/pyscf/molecules.py
pymolresponse/interfaces/pyscf/utils.py
pymolresponse/properties/__init__.py
pymolresponse/properties/ecd.py
pymolresponse/properties/electric.py
pymolresponse/properties/magnetic.py
pymolresponse/properties/optrot.py
pymolresponse/tests/__init__.py
pymolresponse/tests/test_ao2mo.py
pymolresponse/tests/test_calculators.py
pymolresponse/tests/test_final_result.py
pymolresponse/tests/test_hydrogen.py
pymolresponse/tests/test_molecular_property.py
pymolresponse/tests/test_operators.py
pymolresponse/tests/test_rhf.py
pymolresponse/tests/test_runners.py
pymolresponse/tests/test_solvers.py
pymolresponse/tests/test_td.py
pymolresponse/tests/test_uhf.py
pymolresponse/tests/test_uhf_partial_mo_trafo.py
pymolresponse/tests/test_uncoupled.py
pymolresponse/tests/test_utils.py
pymolresponse/tests/properties/test_ecd.py
pymolresponse/tests/properties/test_geometric_hessian.py
pymolresponse/tests/properties/test_magnetic.py
pymolresponse/tests/properties/test_optrot.py
pymolresponse/tests/properties/test_quadratic.py
pymolresponse-0.3.2.dist-info/licenses/LICENSE
pymolresponse-0.3.2.dist-info/METADATA
pymolresponse-0.3.2.dist-info/WHEEL
pymolresponse-0.3.2.dist-info/top_level.txt
pymolresponse-0.3.2.dist-info/RECORD
