Metadata-Version: 2.4
Name: pymolresponse
Version: 0.3.2
Summary: Molecular frequency-dependent response properties for arbitrary operators
Author-email: Eric Berquist <eric.berquist@gmail.com>
License: BSD 3-Clause License
Project-URL: Bug Tracker, https://github.com/berquist/pymolresponse/issues
Project-URL: Documentation, https://berquist.github.io/pymolresponse_docs/
Project-URL: Homepage, https://github.com/berquist/pymolresponse
Classifier: License :: OSI Approved :: BSD License
Classifier: Programming Language :: Python :: 3
Requires-Python: >=3.9
License-File: LICENSE
Requires-Dist: attrs<25,>=24.3.0
Requires-Dist: cclib<2,>=1.8.1
Requires-Dist: periodictable<3,>=2.0.2
Provides-Extra: test
Requires-Dist: coverage; extra == "test"
Requires-Dist: daltools; extra == "test"
Requires-Dist: pyscf; extra == "test"
Requires-Dist: pytest; extra == "test"
Requires-Dist: pytest-cov; extra == "test"
Requires-Dist: pytest-ruff; extra == "test"
Provides-Extra: docs
Requires-Dist: numpydoc; extra == "docs"
Requires-Dist: sphinx; extra == "docs"
Requires-Dist: sphinx_rtd_theme; extra == "docs"
Provides-Extra: dev
Requires-Dist: pymolresponse[docs,test]; extra == "dev"
Dynamic: license-file
